claude_todo_emulator-0.2.2.dist-info/licenses/LICENSE
src/__init__.py
src/server.py
src/types.py
src/state/00-system-instructions.mdc
src/state/01-task-management.mdc
src/state/__init__.py
src/state/persistence.py
src/state/store.py
src/state/utils.py
src/state/validators.py
src/tools/__init__.py
src/tools/todo_read.py
src/tools/todo_write.py
claude_todo_emulator-0.2.2.dist-info/METADATA
claude_todo_emulator-0.2.2.dist-info/WHEEL
claude_todo_emulator-0.2.2.dist-info/entry_points.txt
claude_todo_emulator-0.2.2.dist-info/top_level.txt
claude_todo_emulator-0.2.2.dist-info/RECORD
