Metadata-Version: 2.4
Name: claude-todo-emulator
Version: 0.2.2
Summary: This is an MCP server that emulates Claude Code's task management system, providing persistent todo functionality for AI coding assistants in IDEs like Cursor, Windsurf, and others.
Author-email: Joe Haddad <joehaddad129@gmail.com>
License-Expression: MIT
Project-URL: Homepage, https://github.com/joehaddad2000/claude-todo-emulator
Project-URL: Repository, https://github.com/joehaddad2000/claude-todo-emulator
Project-URL: Issues, https://github.com/joehaddad2000/claude-todo-emulator/issues
Keywords: mcp,claude,todo,task-management,ai-assistant
Classifier: Development Status :: 4 - Beta
Classifier: Intended Audience :: Developers
Classifier: Programming Language :: Python :: 3
Classifier: Programming Language :: Python :: 3.11
Classifier: Programming Language :: Python :: 3.12
Classifier: Programming Language :: Python :: 3.13
Requires-Python: >=3.11
License-File: LICENSE
Requires-Dist: fastmcp>=2.8.1
Dynamic: license-file
